qnetti/__init__.py
qnetti/_version.py
qnetti/characteristic_matrices.py
qnetti/covariance_matrices.py
qnetti/file_utilities.py
qnetti/optimize.py
qnetti/plot_utils.py
qnetti/qnodes.py
qnetti/script_utils.py
qnetti/topology_inference.py
qNetTI-0.1.0.dist-info/METADATA
qNetTI-0.1.0.dist-info/WHEEL
qNetTI-0.1.0.dist-info/top_level.txt
qNetTI-0.1.0.dist-info/RECORD
