Metadata-Version: 2.1
Name: qNetTI
Version: 0.1.0
Summary: Quantum Network Topology Inferrer
Home-page: https://github.com/ChitambarLab/qNetTI
Author: Brian Doolittle and Danny Chen
Author-email: brian.d.doolittle@gmail.com
Project-URL: Bug Tracker, https://github.com/ChitambarLab/qNetTI
Classifier: Programming Language :: Python :: 3
Classifier: License :: OSI Approved :: Apache Software License
Classifier: Operating System :: OS Independent
Requires-Python: >=3.8
Requires-Dist: pennylane ==0.29.1
Requires-Dist: qnetvo ==0.4.2
Requires-Dist: matplotlib ==3.7
